asynciominimalmodbus.py
AsyncioMinimalModbus-1.0.0.dist-info/LICENSE
AsyncioMinimalModbus-1.0.0.dist-info/METADATA
AsyncioMinimalModbus-1.0.0.dist-info/WHEEL
AsyncioMinimalModbus-1.0.0.dist-info/top_level.txt
AsyncioMinimalModbus-1.0.0.dist-info/RECORD
