Metadata-Version: 2.1
Name: AsyncioMinimalModbus
Version: 1.0.0
Summary: Async Easy-to-use Modbus RTU and Modbus ASCII implementation for Python
Home-page: https://github.com/guyradford/asynciominimalmodbus
Author: Guy Radford
Project-URL: Bug Tracker, https://github.com/guyradford/asynciominimalmodbus/issues
Classifier: Development Status :: 5 - Production/Stable
Classifier: Intended Audience :: Developers
Classifier: Intended Audience :: Information Technology
Classifier: Intended Audience :: Science/Research
Classifier: Intended Audience :: Manufacturing
Classifier: License :: OSI Approved :: Apache Software License
Classifier: Natural Language :: English
Classifier: Operating System :: OS Independent
Classifier: Operating System :: POSIX
Classifier: Operating System :: Microsoft :: Windows
Classifier: Programming Language :: Python
Classifier: Programming Language :: Python :: 3
Classifier: Programming Language :: Python :: 3.6
Classifier: Programming Language :: Python :: 3.7
Classifier: Programming Language :: Python :: 3.8
Classifier: Programming Language :: Python :: 3.9
Classifier: Programming Language :: Python :: 3.10
Classifier: Topic :: Communications
Classifier: Topic :: Home Automation
Classifier: Topic :: Scientific/Engineering
Classifier: Topic :: Software Development :: Libraries
Classifier: Topic :: Software Development :: Libraries :: Python Modules
Classifier: Topic :: System :: Hardware :: Hardware Drivers
Classifier: Topic :: Terminals :: Serial
Classifier: Framework :: AsyncIO
Requires-Python: >=3.6
License-File: LICENSE
Requires-Dist: minimalmodbus (>=2.0.1)
